django_lightning_seed/__init__.py
django_lightning_seed/admin.py
django_lightning_seed/apps.py
django_lightning_seed/models.py
django_lightning_seed/tests.py
django_lightning_seed/views.py
django_lightning_seed/management/commands/lightning_seed.py
django_lightning_seed/migrations/__init__.py
django_lightning_seed-1.0.0.dist-info/METADATA
django_lightning_seed-1.0.0.dist-info/WHEEL
django_lightning_seed-1.0.0.dist-info/licenses/LICENSE
django_lightning_seed-1.0.0.dist-info/RECORD
