Metadata-Version: 2.4
Name: django-lightning-seed
Version: 1.0.0
Summary: ⚡️A blazing-fast Django management command for seeding data
Project-URL: Homepage, https://github.com/spider-hand/django-lightning-seed
Project-URL: Repository, https://github.com/spider-hand/django-lightning-seed
Project-URL: Documentation, https://github.com/spider-hand/django-lightning-seed/blob/main/README.md
Project-URL: Bug Tracker, https://github.com/spider-hand/django-lightning-seed/issues
Project-URL: Changelog, https://github.com/spider-hand/django-lightning-seed/blob/main/CHANGELOG.md
Author-email: Akinori Hoshina <creative.spider.hand@gmail.com>
License-Expression: MIT
License-File: LICENSE
Keywords: django,seed
Requires-Python: >=3.13
Requires-Dist: coverage>=7.11.0
Requires-Dist: django>=5.2.7
Requires-Dist: faker>=37.12.0
Requires-Dist: numpy>=2.3.4
Requires-Dist: polars>=1.34.0
Requires-Dist: psycopg2-binary>=2.9.11
